Metadata-Version: 1.0
Name: tf-kaldi-io
Version: 0.2.0
Summary: kaldi-io for Tensorflow
Home-page: https://github.com/open-speech/tf_kaldi_io
Author: Meixu Song
Author-email: songmeixu@outlook.com
License: MIT
Platform: UNKNOWN
